multisoc/__init__.py
multisoc/generate/IO_utils.py
multisoc/generate/__init__.py
multisoc/generate/multidimensional_network.py
multisoc/generate/multidimensional_network_ORIGINAL.py
multisoc/generate/tests.py
multisoc/generate/two_dimensional_population.py
multisoc/generate/utils.py
multisoc/generate/validators.py
multisoc/infer/MRQAP.py
multisoc/infer/__init__.py
multisoc/infer/aggregation_functions.py
multisoc/infer/aux_functions.py
multisoc/infer/data_loader.py
multisoc/infer/inference.py
multisoc/infer/wrappers.py
multisoc/metrics/__init__.py
multisoc/metrics/fairness_metrics.py
multisoc/metrics/network_statistics.py
multisoc/theory/__init__.py
multisoc/theory/fairness_metrics.py
multisoc/theory/multidimensional_preferences.py
multisoc/theory/network_statistics.py
multisoc-0.1.1.dist-info/METADATA
multisoc-0.1.1.dist-info/WHEEL
multisoc-0.1.1.dist-info/top_level.txt
multisoc-0.1.1.dist-info/RECORD
