Metadata-Version: 2.1
Name: multisoc
Version: 0.1.1
Summary: A package to simulate and analyze networks with multidimensional interactions.
Home-page: https://github.com/CSHVienna/multisoc
Author: Samuel Martin-Gutierrez
Author-email: martin.gutierrez@csh.ac.at
Classifier: Programming Language :: Python :: 3
Classifier: Operating System :: OS Independent
Requires-Python: >=3.9
Requires-Dist: matplotlib >=3.7.5
Requires-Dist: mpmath >=1.3.0
Requires-Dist: networkx >=3.2.1
Requires-Dist: numpy ==1.26.4
Requires-Dist: pandas >=2.0.3
Requires-Dist: pytest >=7.2.2
Requires-Dist: scipy >=1.13.1
Requires-Dist: statsmodels ==0.14.2
Requires-Dist: tqdm >=4.66.5
Requires-Dist: jinja2 >=3.1.4
